{
  "generatedAt": "2026-06-12T11:40:00.855Z",
  "command": "node scripts/qa/erp-field-linkage.mjs",
  "runContext": {
    "repoRoot": "/Users/simon/projects/plush-toy-erp",
    "gitCommit": "6d2a491aaa012e0e96c85248beefb83180e183db",
    "gitCommitShort": "6d2a491aaa01",
    "gitBranch": "main",
    "gitDirty": true,
    "nodeVersion": "v24.14.0",
    "generatedBy": "simon"
  },
  "summary": {
    "totalFields": 30,
    "coveredFields": 8,
    "partialFields": 1,
    "missingFields": 21,
    "failingFields": 0,
    "totalCases": 13,
    "passedCases": 13,
    "failedCases": 0,
    "skippedCases": 0,
    "missingCases": 0,
    "totalScenarios": 53,
    "passedScenarios": 11
  },
  "fields": [
    {
      "fieldKey": "itemQuantity",
      "fieldLabel": "明细数量",
      "category": "当前记录派生",
      "risk": "P0",
      "docLabels": ["数量", "明细数量"],
      "requiredScenarioKeys": [
        "derived_amount_recomputed",
        "header_totals_derived_from_items"
      ],
      "status": "partial",
      "layers": ["web"],
      "passedCases": 3,
      "totalCases": 3,
      "passedScenarios": 1,
      "totalScenarios": 2,
      "scenarios": [
        {
          "scenarioKey": "derived_amount_recomputed",
          "scenarioLabel": "数量与单价驱动金额重算",
          "status": "pass",
          "caseIds": [
            "FL_processing_contract_amount__derives_default_line_amount_snapshot",
            "FL_material_purchase_amount__recomputes_amount_and_total_from_current_line",
            "FL_processing_contract_editor__recomputes_default_amount_on_quantity_change"
          ]
        },
        {
          "scenarioKey": "header_totals_derived_from_items",
          "scenarioLabel": "表头数量金额按当前明细派生",
          "status": "missing",
          "caseIds": []
        }
      ],
      "cases": [
        {
          "caseId": "FL_processing_contract_amount__derives_default_line_amount_snapshot",
          "title": "加工合同默认金额按数量和单价写入合同快照",
          "fieldKeys": ["processingAmount", "itemQuantity", "itemUnitPrice"],
          "scenarioKey": "derived_amount_recomputed",
          "layer": "web",
          "testFile": "web/src/erp/data/processingContractTemplate.test.mjs",
          "status": "pass",
          "durationMs": 0,
          "failureMessages": []
        },
        {
          "caseId": "FL_material_purchase_amount__recomputes_amount_and_total_from_current_line",
          "title": "采购合同数量或单价变化会重算金额和总计",
          "fieldKeys": ["purchaseAmount", "itemQuantity", "itemUnitPrice"],
          "scenarioKey": "derived_amount_recomputed",
          "layer": "web",
          "testFile": "web/src/erp/utils/materialPurchaseContractEditor.test.mjs",
          "status": "pass",
          "durationMs": 1,
          "failureMessages": []
        },
        {
          "caseId": "FL_processing_contract_editor__recomputes_default_amount_on_quantity_change",
          "title": "加工合同调整数量时同步重算默认委托加工金额",
          "fieldKeys": ["processingAmount", "itemQuantity", "itemUnitPrice"],
          "scenarioKey": "derived_amount_recomputed",
          "layer": "web",
          "testFile": "web/src/erp/utils/processingContractEditor.test.mjs",
          "status": "pass",
          "durationMs": 0,
          "failureMessages": []
        }
      ]
    },
    {
      "fieldKey": "headerAmount",
      "fieldLabel": "表头金额",
      "category": "当前记录汇总",
      "risk": "P0",
      "docLabels": ["表头金额"],
      "requiredScenarioKeys": [
        "header_totals_derived_from_items",
        "manual_snapshot_retained"
      ],
      "status": "missing",
      "layers": [],
      "passedCases": 0,
      "totalCases": 0,
      "passedScenarios": 0,
      "totalScenarios": 2,
      "scenarios": [
        {
          "scenarioKey": "header_totals_derived_from_items",
          "scenarioLabel": "表头数量金额按当前明细派生",
          "status": "missing",
          "caseIds": []
        },
        {
          "scenarioKey": "manual_snapshot_retained",
          "scenarioLabel": "手工金额快照优先保留",
          "status": "missing",
          "caseIds": []
        }
      ],
      "cases": []
    },
    {
      "fieldKey": "headerQuantity",
      "fieldLabel": "表头数量",
      "category": "当前记录汇总",
      "risk": "P0",
      "docLabels": ["表头数量"],
      "requiredScenarioKeys": [
        "header_totals_derived_from_items",
        "manual_snapshot_retained"
      ],
      "status": "missing",
      "layers": [],
      "passedCases": 0,
      "totalCases": 0,
      "passedScenarios": 0,
      "totalScenarios": 2,
      "scenarios": [
        {
          "scenarioKey": "header_totals_derived_from_items",
          "scenarioLabel": "表头数量金额按当前明细派生",
          "status": "missing",
          "caseIds": []
        },
        {
          "scenarioKey": "manual_snapshot_retained",
          "scenarioLabel": "手工金额快照优先保留",
          "status": "missing",
          "caseIds": []
        }
      ],
      "cases": []
    },
    {
      "fieldKey": "productNo",
      "fieldLabel": "产品编号 / SKU",
      "category": "业务快照字段",
      "risk": "P0",
      "docLabels": ["产品编号 / SKU"],
      "requiredScenarioKeys": [
        "source_snapshot_retained",
        "source_prefill_rebuilds_from_blank",
        "source_change_clears_prefill"
      ],
      "status": "missing",
      "layers": ["web"],
      "passedCases": 2,
      "totalCases": 2,
      "passedScenarios": 0,
      "totalScenarios": 3,
      "scenarios": [
        {
          "scenarioKey": "source_snapshot_retained",
          "scenarioLabel": "来源快照保留并随状态流转带出",
          "status": "missing",
          "caseIds": []
        },
        {
          "scenarioKey": "source_prefill_rebuilds_from_blank",
          "scenarioLabel": "新建来源带值从空白默认值重建",
          "status": "missing",
          "caseIds": []
        },
        {
          "scenarioKey": "source_change_clears_prefill",
          "scenarioLabel": "切换来源会清空旧来源带值",
          "status": "missing",
          "caseIds": []
        }
      ],
      "cases": [
        {
          "caseId": "FL_processing_contract_editor__clears_blank_inserted_lines",
          "title": "加工合同插入明细行会清空来源字段，避免复制当前行残值",
          "fieldKeys": ["productOrderNo", "productNo", "productNameColor"],
          "scenarioKey": "stale_value_cleared",
          "layer": "web",
          "testFile": "web/src/erp/utils/processingContractEditor.test.mjs",
          "status": "pass",
          "durationMs": 1,
          "failureMessages": []
        },
        {
          "caseId": "FL_processing_contract_editor__clears_deleted_last_line",
          "title": "加工合同删除到只剩一行时会重置为空白行",
          "fieldKeys": ["productOrderNo", "productNo", "productNameColor"],
          "scenarioKey": "stale_value_cleared",
          "layer": "web",
          "testFile": "web/src/erp/utils/processingContractEditor.test.mjs",
          "status": "pass",
          "durationMs": 0,
          "failureMessages": []
        }
      ]
    },
    {
      "fieldKey": "productOrderNo",
      "fieldLabel": "产品订单编号",
      "category": "业务快照字段",
      "risk": "P0",
      "docLabels": ["产品订单编号"],
      "requiredScenarioKeys": [
        "source_snapshot_retained",
        "source_prefill_rebuilds_from_blank"
      ],
      "status": "missing",
      "layers": ["web"],
      "passedCases": 4,
      "totalCases": 4,
      "passedScenarios": 0,
      "totalScenarios": 2,
      "scenarios": [
        {
          "scenarioKey": "source_snapshot_retained",
          "scenarioLabel": "来源快照保留并随状态流转带出",
          "status": "missing",
          "caseIds": []
        },
        {
          "scenarioKey": "source_prefill_rebuilds_from_blank",
          "scenarioLabel": "新建来源带值从空白默认值重建",
          "status": "missing",
          "caseIds": []
        }
      ],
      "cases": [
        {
          "caseId": "FL_material_purchase_merge__clears_covered_cell_stale_value",
          "title": "采购合同合并选区后会清空被覆盖单元格",
          "fieldKeys": ["productOrderNo", "mergedCellContent"],
          "scenarioKey": "merge_clears_covered_cells",
          "layer": "web",
          "testFile": "web/src/erp/utils/materialPurchaseContractEditor.test.mjs",
          "status": "pass",
          "durationMs": 0,
          "failureMessages": []
        },
        {
          "caseId": "FL_processing_contract_editor__clears_blank_inserted_lines",
          "title": "加工合同插入明细行会清空来源字段，避免复制当前行残值",
          "fieldKeys": ["productOrderNo", "productNo", "productNameColor"],
          "scenarioKey": "stale_value_cleared",
          "layer": "web",
          "testFile": "web/src/erp/utils/processingContractEditor.test.mjs",
          "status": "pass",
          "durationMs": 1,
          "failureMessages": []
        },
        {
          "caseId": "FL_processing_contract_editor__clears_deleted_last_line",
          "title": "加工合同删除到只剩一行时会重置为空白行",
          "fieldKeys": ["productOrderNo", "productNo", "productNameColor"],
          "scenarioKey": "stale_value_cleared",
          "layer": "web",
          "testFile": "web/src/erp/utils/processingContractEditor.test.mjs",
          "status": "pass",
          "durationMs": 0,
          "failureMessages": []
        },
        {
          "caseId": "FL_processing_contract_editor__clears_covered_cell_stale_value",
          "title": "加工合同合并选区后会清空被覆盖单元格",
          "fieldKeys": ["productOrderNo", "mergedCellContent"],
          "scenarioKey": "merge_clears_covered_cells",
          "layer": "web",
          "testFile": "web/src/erp/utils/processingContractEditor.test.mjs",
          "status": "pass",
          "durationMs": 13,
          "failureMessages": []
        }
      ]
    },
    {
      "fieldKey": "productNameColor",
      "fieldLabel": "产品名称 / 颜色",
      "category": "业务快照字段",
      "risk": "P0",
      "docLabels": ["产品名称 / 颜色"],
      "requiredScenarioKeys": [
        "source_snapshot_retained",
        "source_prefill_rebuilds_from_blank",
        "source_change_clears_prefill"
      ],
      "status": "missing",
      "layers": ["web"],
      "passedCases": 2,
      "totalCases": 2,
      "passedScenarios": 0,
      "totalScenarios": 3,
      "scenarios": [
        {
          "scenarioKey": "source_snapshot_retained",
          "scenarioLabel": "来源快照保留并随状态流转带出",
          "status": "missing",
          "caseIds": []
        },
        {
          "scenarioKey": "source_prefill_rebuilds_from_blank",
          "scenarioLabel": "新建来源带值从空白默认值重建",
          "status": "missing",
          "caseIds": []
        },
        {
          "scenarioKey": "source_change_clears_prefill",
          "scenarioLabel": "切换来源会清空旧来源带值",
          "status": "missing",
          "caseIds": []
        }
      ],
      "cases": [
        {
          "caseId": "FL_processing_contract_editor__clears_blank_inserted_lines",
          "title": "加工合同插入明细行会清空来源字段，避免复制当前行残值",
          "fieldKeys": ["productOrderNo", "productNo", "productNameColor"],
          "scenarioKey": "stale_value_cleared",
          "layer": "web",
          "testFile": "web/src/erp/utils/processingContractEditor.test.mjs",
          "status": "pass",
          "durationMs": 1,
          "failureMessages": []
        },
        {
          "caseId": "FL_processing_contract_editor__clears_deleted_last_line",
          "title": "加工合同删除到只剩一行时会重置为空白行",
          "fieldKeys": ["productOrderNo", "productNo", "productNameColor"],
          "scenarioKey": "stale_value_cleared",
          "layer": "web",
          "testFile": "web/src/erp/utils/processingContractEditor.test.mjs",
          "status": "pass",
          "durationMs": 0,
          "failureMessages": []
        }
      ]
    },
    {
      "fieldKey": "productMasterSelection",
      "fieldLabel": "产品主档选择",
      "category": "主档引用 / 业务快照",
      "risk": "P0",
      "docLabels": ["产品名称 / 颜色", "产品"],
      "requiredScenarioKeys": [
        "master_record_selection_synced",
        "master_record_selection_cleared"
      ],
      "status": "missing",
      "layers": [],
      "passedCases": 0,
      "totalCases": 0,
      "passedScenarios": 0,
      "totalScenarios": 2,
      "scenarios": [
        {
          "scenarioKey": "master_record_selection_synced",
          "scenarioLabel": "基础资料选择同步业务快照",
          "status": "missing",
          "caseIds": []
        },
        {
          "scenarioKey": "master_record_selection_cleared",
          "scenarioLabel": "基础资料选择清空同步清值",
          "status": "missing",
          "caseIds": []
        }
      ],
      "cases": []
    },
    {
      "fieldKey": "shipDate",
      "fieldLabel": "出货日期",
      "category": "日期快照字段",
      "risk": "P0",
      "docLabels": ["出货日期"],
      "requiredScenarioKeys": ["source_snapshot_retained"],
      "status": "missing",
      "layers": [],
      "passedCases": 0,
      "totalCases": 0,
      "passedScenarios": 0,
      "totalScenarios": 1,
      "scenarios": [
        {
          "scenarioKey": "source_snapshot_retained",
          "scenarioLabel": "来源快照保留并随状态流转带出",
          "status": "missing",
          "caseIds": []
        }
      ],
      "cases": []
    },
    {
      "fieldKey": "orderNo",
      "fieldLabel": "订单编号",
      "category": "业务快照字段",
      "risk": "P0",
      "docLabels": ["订单编号"],
      "requiredScenarioKeys": [
        "source_snapshot_retained",
        "source_prefill_rebuilds_from_blank"
      ],
      "status": "missing",
      "layers": [],
      "passedCases": 0,
      "totalCases": 0,
      "passedScenarios": 0,
      "totalScenarios": 2,
      "scenarios": [
        {
          "scenarioKey": "source_snapshot_retained",
          "scenarioLabel": "来源快照保留并随状态流转带出",
          "status": "missing",
          "caseIds": []
        },
        {
          "scenarioKey": "source_prefill_rebuilds_from_blank",
          "scenarioLabel": "新建来源带值从空白默认值重建",
          "status": "missing",
          "caseIds": []
        }
      ],
      "cases": []
    },
    {
      "fieldKey": "accessoryMaterial",
      "fieldLabel": "辅材 / 包材字段",
      "category": "采购快照字段",
      "risk": "P0",
      "docLabels": ["辅材 / 包材字段"],
      "requiredScenarioKeys": [
        "source_snapshot_retained",
        "stale_value_cleared",
        "source_change_clears_prefill"
      ],
      "status": "missing",
      "layers": [],
      "passedCases": 0,
      "totalCases": 0,
      "passedScenarios": 0,
      "totalScenarios": 3,
      "scenarios": [
        {
          "scenarioKey": "source_snapshot_retained",
          "scenarioLabel": "来源快照保留并随状态流转带出",
          "status": "missing",
          "caseIds": []
        },
        {
          "scenarioKey": "stale_value_cleared",
          "scenarioLabel": "当前表单残值清理",
          "status": "missing",
          "caseIds": []
        },
        {
          "scenarioKey": "source_change_clears_prefill",
          "scenarioLabel": "切换来源会清空旧来源带值",
          "status": "missing",
          "caseIds": []
        }
      ],
      "cases": []
    },
    {
      "fieldKey": "supplierMasterSelection",
      "fieldLabel": "供应商主档选择",
      "category": "主档引用 / 业务快照",
      "risk": "P0",
      "docLabels": ["供应商 / 加工厂", "客户/供应商"],
      "requiredScenarioKeys": ["master_record_selection_synced"],
      "status": "missing",
      "layers": [],
      "passedCases": 0,
      "totalCases": 0,
      "passedScenarios": 0,
      "totalScenarios": 1,
      "scenarios": [
        {
          "scenarioKey": "master_record_selection_synced",
          "scenarioLabel": "基础资料选择同步业务快照",
          "status": "missing",
          "caseIds": []
        }
      ],
      "cases": []
    },
    {
      "fieldKey": "returnDate",
      "fieldLabel": "回货日期",
      "category": "日期快照字段",
      "risk": "P0",
      "docLabels": ["回货日期"],
      "requiredScenarioKeys": ["source_snapshot_retained"],
      "status": "missing",
      "layers": [],
      "passedCases": 0,
      "totalCases": 0,
      "passedScenarios": 0,
      "totalScenarios": 1,
      "scenarios": [
        {
          "scenarioKey": "source_snapshot_retained",
          "scenarioLabel": "来源快照保留并随状态流转带出",
          "status": "missing",
          "caseIds": []
        }
      ],
      "cases": []
    },
    {
      "fieldKey": "customerName",
      "fieldLabel": "客户",
      "category": "业务快照字段",
      "risk": "P0",
      "docLabels": ["客户"],
      "requiredScenarioKeys": [
        "source_snapshot_retained",
        "source_prefill_rebuilds_from_blank",
        "source_change_clears_prefill"
      ],
      "status": "missing",
      "layers": [],
      "passedCases": 0,
      "totalCases": 0,
      "passedScenarios": 0,
      "totalScenarios": 3,
      "scenarios": [
        {
          "scenarioKey": "source_snapshot_retained",
          "scenarioLabel": "来源快照保留并随状态流转带出",
          "status": "missing",
          "caseIds": []
        },
        {
          "scenarioKey": "source_prefill_rebuilds_from_blank",
          "scenarioLabel": "新建来源带值从空白默认值重建",
          "status": "missing",
          "caseIds": []
        },
        {
          "scenarioKey": "source_change_clears_prefill",
          "scenarioLabel": "切换来源会清空旧来源带值",
          "status": "missing",
          "caseIds": []
        }
      ],
      "cases": []
    },
    {
      "fieldKey": "partnerContacts",
      "fieldLabel": "客户/供应商联系人",
      "category": "主数据摘要字段",
      "risk": "P0",
      "docLabels": ["联系人", "办公室电话", "手机", "邮箱"],
      "requiredScenarioKeys": [
        "partner_contacts_synced",
        "partner_contacts_cleared"
      ],
      "status": "missing",
      "layers": [],
      "passedCases": 0,
      "totalCases": 0,
      "passedScenarios": 0,
      "totalScenarios": 2,
      "scenarios": [
        {
          "scenarioKey": "partner_contacts_synced",
          "scenarioLabel": "客户/供应商联系人明细同步摘要",
          "status": "missing",
          "caseIds": []
        },
        {
          "scenarioKey": "partner_contacts_cleared",
          "scenarioLabel": "客户/供应商联系人摘要随明细清空",
          "status": "missing",
          "caseIds": []
        }
      ],
      "cases": []
    },
    {
      "fieldKey": "customerMasterSelection",
      "fieldLabel": "客户主档选择",
      "category": "主档引用 / 业务快照",
      "risk": "P0",
      "docLabels": ["客户", "客户/供应商"],
      "requiredScenarioKeys": [
        "master_record_selection_synced",
        "master_record_selection_cleared"
      ],
      "status": "missing",
      "layers": [],
      "passedCases": 0,
      "totalCases": 0,
      "passedScenarios": 0,
      "totalScenarios": 2,
      "scenarios": [
        {
          "scenarioKey": "master_record_selection_synced",
          "scenarioLabel": "基础资料选择同步业务快照",
          "status": "missing",
          "caseIds": []
        },
        {
          "scenarioKey": "master_record_selection_cleared",
          "scenarioLabel": "基础资料选择清空同步清值",
          "status": "missing",
          "caseIds": []
        }
      ],
      "cases": []
    },
    {
      "fieldKey": "styleNo",
      "fieldLabel": "款式编号",
      "category": "主档 / 主数据候选",
      "risk": "P0",
      "docLabels": ["款式编号"],
      "requiredScenarioKeys": [
        "source_snapshot_retained",
        "source_prefill_rebuilds_from_blank"
      ],
      "status": "missing",
      "layers": [],
      "passedCases": 0,
      "totalCases": 0,
      "passedScenarios": 0,
      "totalScenarios": 2,
      "scenarios": [
        {
          "scenarioKey": "source_snapshot_retained",
          "scenarioLabel": "来源快照保留并随状态流转带出",
          "status": "missing",
          "caseIds": []
        },
        {
          "scenarioKey": "source_prefill_rebuilds_from_blank",
          "scenarioLabel": "新建来源带值从空白默认值重建",
          "status": "missing",
          "caseIds": []
        }
      ],
      "cases": []
    },
    {
      "fieldKey": "sourceNo",
      "fieldLabel": "来源单号",
      "category": "通用业务记录快照",
      "risk": "P0",
      "docLabels": ["来源单号"],
      "requiredScenarioKeys": [
        "source_snapshot_retained",
        "source_prefill_rebuilds_from_blank",
        "source_change_clears_prefill"
      ],
      "status": "missing",
      "layers": [],
      "passedCases": 0,
      "totalCases": 0,
      "passedScenarios": 0,
      "totalScenarios": 3,
      "scenarios": [
        {
          "scenarioKey": "source_snapshot_retained",
          "scenarioLabel": "来源快照保留并随状态流转带出",
          "status": "missing",
          "caseIds": []
        },
        {
          "scenarioKey": "source_prefill_rebuilds_from_blank",
          "scenarioLabel": "新建来源带值从空白默认值重建",
          "status": "missing",
          "caseIds": []
        },
        {
          "scenarioKey": "source_change_clears_prefill",
          "scenarioLabel": "切换来源会清空旧来源带值",
          "status": "missing",
          "caseIds": []
        }
      ],
      "cases": []
    },
    {
      "fieldKey": "itemAmount",
      "fieldLabel": "明细金额",
      "category": "当前记录派生 / 快照",
      "risk": "P0",
      "docLabels": ["金额", "明细金额"],
      "requiredScenarioKeys": [
        "derived_amount_recomputed",
        "manual_snapshot_retained"
      ],
      "status": "missing",
      "layers": [],
      "passedCases": 0,
      "totalCases": 0,
      "passedScenarios": 0,
      "totalScenarios": 2,
      "scenarios": [
        {
          "scenarioKey": "derived_amount_recomputed",
          "scenarioLabel": "数量与单价驱动金额重算",
          "status": "missing",
          "caseIds": []
        },
        {
          "scenarioKey": "manual_snapshot_retained",
          "scenarioLabel": "手工金额快照优先保留",
          "status": "missing",
          "caseIds": []
        }
      ],
      "cases": []
    },
    {
      "fieldKey": "businessStatus",
      "fieldLabel": "业务状态",
      "category": "workflow 状态快照",
      "risk": "P0",
      "docLabels": ["业务状态"],
      "requiredScenarioKeys": ["source_snapshot_retained"],
      "status": "missing",
      "layers": [],
      "passedCases": 0,
      "totalCases": 0,
      "passedScenarios": 0,
      "totalScenarios": 1,
      "scenarios": [
        {
          "scenarioKey": "source_snapshot_retained",
          "scenarioLabel": "来源快照保留并随状态流转带出",
          "status": "missing",
          "caseIds": []
        }
      ],
      "cases": []
    },
    {
      "fieldKey": "mainMaterial",
      "fieldLabel": "主料物料字段",
      "category": "BOM 真源 / 派生影响",
      "risk": "P0",
      "docLabels": ["主料物料字段"],
      "requiredScenarioKeys": [
        "source_snapshot_retained",
        "stale_value_cleared"
      ],
      "status": "missing",
      "layers": [],
      "passedCases": 0,
      "totalCases": 0,
      "passedScenarios": 0,
      "totalScenarios": 2,
      "scenarios": [
        {
          "scenarioKey": "source_snapshot_retained",
          "scenarioLabel": "来源快照保留并随状态流转带出",
          "status": "missing",
          "caseIds": []
        },
        {
          "scenarioKey": "stale_value_cleared",
          "scenarioLabel": "当前表单残值清理",
          "status": "missing",
          "caseIds": []
        }
      ],
      "cases": []
    },
    {
      "fieldKey": "purchaseAmount",
      "fieldLabel": "采购金额",
      "category": "采购合同快照",
      "risk": "P0",
      "docLabels": ["采购金额"],
      "requiredScenarioKeys": [
        "derived_amount_recomputed",
        "manual_snapshot_retained"
      ],
      "status": "covered",
      "layers": ["web"],
      "passedCases": 2,
      "totalCases": 2,
      "passedScenarios": 2,
      "totalScenarios": 2,
      "scenarios": [
        {
          "scenarioKey": "derived_amount_recomputed",
          "scenarioLabel": "数量与单价驱动金额重算",
          "status": "pass",
          "caseIds": [
            "FL_material_purchase_amount__recomputes_amount_and_total_from_current_line"
          ]
        },
        {
          "scenarioKey": "manual_snapshot_retained",
          "scenarioLabel": "手工金额快照优先保留",
          "status": "pass",
          "caseIds": [
            "FL_material_purchase_amount__keeps_manual_amount_snapshot"
          ]
        }
      ],
      "cases": [
        {
          "caseId": "FL_material_purchase_amount__recomputes_amount_and_total_from_current_line",
          "title": "采购合同数量或单价变化会重算金额和总计",
          "fieldKeys": ["purchaseAmount", "itemQuantity", "itemUnitPrice"],
          "scenarioKey": "derived_amount_recomputed",
          "layer": "web",
          "testFile": "web/src/erp/utils/materialPurchaseContractEditor.test.mjs",
          "status": "pass",
          "durationMs": 1,
          "failureMessages": []
        },
        {
          "caseId": "FL_material_purchase_amount__keeps_manual_amount_snapshot",
          "title": "采购合同初始化时优先保留已有采购金额快照",
          "fieldKeys": ["purchaseAmount"],
          "scenarioKey": "manual_snapshot_retained",
          "layer": "web",
          "testFile": "web/src/erp/utils/materialPurchaseContractEditor.test.mjs",
          "status": "pass",
          "durationMs": 1,
          "failureMessages": []
        }
      ]
    },
    {
      "fieldKey": "printWindowHtml",
      "fieldLabel": "打印窗口 HTML 快照",
      "category": "打印快照字段",
      "risk": "P0",
      "docLabels": ["打印窗口 HTML 快照"],
      "requiredScenarioKeys": ["print_window_snapshot_retained"],
      "status": "covered",
      "layers": ["web"],
      "passedCases": 1,
      "totalCases": 1,
      "passedScenarios": 1,
      "totalScenarios": 1,
      "scenarios": [
        {
          "scenarioKey": "print_window_snapshot_retained",
          "scenarioLabel": "打印窗口快照持久化",
          "status": "pass",
          "caseIds": [
            "FL_print_workspace_window_snapshot__persists_current_html_snapshot"
          ]
        }
      ],
      "cases": [
        {
          "caseId": "FL_print_workspace_window_snapshot__persists_current_html_snapshot",
          "title": "打印工作台会把整窗 HTML 快照落到窗口状态",
          "fieldKeys": ["attachmentSnapshot", "printWindowHtml"],
          "scenarioKey": "print_window_snapshot_retained",
          "layer": "web",
          "testFile": "web/src/erp/utils/printWorkspace.test.mjs",
          "status": "pass",
          "durationMs": 0,
          "failureMessages": []
        }
      ]
    },
    {
      "fieldKey": "processorContactAddress",
      "fieldLabel": "加工方联系人 / 地址",
      "category": "合同头快照",
      "risk": "P0",
      "docLabels": ["加工方联系人 / 地址"],
      "requiredScenarioKeys": ["default_sample_uses_generic_party_values"],
      "status": "covered",
      "layers": ["web"],
      "passedCases": 1,
      "totalCases": 1,
      "passedScenarios": 1,
      "totalScenarios": 1,
      "scenarios": [
        {
          "scenarioKey": "default_sample_uses_generic_party_values",
          "scenarioLabel": "默认样例使用中性交易方展示值",
          "status": "pass",
          "caseIds": [
            "FL_print_templates_sample__uses_generic_sample_values_without_customer_identity"
          ]
        }
      ],
      "cases": [
        {
          "caseId": "FL_print_templates_sample__uses_generic_sample_values_without_customer_identity",
          "title": "打印模板默认样例使用中性展示值且不带客户身份",
          "fieldKeys": ["processorContactAddress"],
          "scenarioKey": "default_sample_uses_generic_party_values",
          "layer": "web",
          "testFile": "web/src/erp/config/printTemplates.test.mjs",
          "status": "pass",
          "durationMs": 1,
          "failureMessages": []
        }
      ]
    },
    {
      "fieldKey": "itemUnitPrice",
      "fieldLabel": "明细单价",
      "category": "当前记录派生",
      "risk": "P0",
      "docLabels": ["单价", "明细单价"],
      "requiredScenarioKeys": ["derived_amount_recomputed"],
      "status": "covered",
      "layers": ["web"],
      "passedCases": 3,
      "totalCases": 3,
      "passedScenarios": 1,
      "totalScenarios": 1,
      "scenarios": [
        {
          "scenarioKey": "derived_amount_recomputed",
          "scenarioLabel": "数量与单价驱动金额重算",
          "status": "pass",
          "caseIds": [
            "FL_processing_contract_amount__derives_default_line_amount_snapshot",
            "FL_material_purchase_amount__recomputes_amount_and_total_from_current_line",
            "FL_processing_contract_editor__recomputes_default_amount_on_quantity_change"
          ]
        }
      ],
      "cases": [
        {
          "caseId": "FL_processing_contract_amount__derives_default_line_amount_snapshot",
          "title": "加工合同默认金额按数量和单价写入合同快照",
          "fieldKeys": ["processingAmount", "itemQuantity", "itemUnitPrice"],
          "scenarioKey": "derived_amount_recomputed",
          "layer": "web",
          "testFile": "web/src/erp/data/processingContractTemplate.test.mjs",
          "status": "pass",
          "durationMs": 0,
          "failureMessages": []
        },
        {
          "caseId": "FL_material_purchase_amount__recomputes_amount_and_total_from_current_line",
          "title": "采购合同数量或单价变化会重算金额和总计",
          "fieldKeys": ["purchaseAmount", "itemQuantity", "itemUnitPrice"],
          "scenarioKey": "derived_amount_recomputed",
          "layer": "web",
          "testFile": "web/src/erp/utils/materialPurchaseContractEditor.test.mjs",
          "status": "pass",
          "durationMs": 1,
          "failureMessages": []
        },
        {
          "caseId": "FL_processing_contract_editor__recomputes_default_amount_on_quantity_change",
          "title": "加工合同调整数量时同步重算默认委托加工金额",
          "fieldKeys": ["processingAmount", "itemQuantity", "itemUnitPrice"],
          "scenarioKey": "derived_amount_recomputed",
          "layer": "web",
          "testFile": "web/src/erp/utils/processingContractEditor.test.mjs",
          "status": "pass",
          "durationMs": 0,
          "failureMessages": []
        }
      ]
    },
    {
      "fieldKey": "processingAmount",
      "fieldLabel": "委托加工金额",
      "category": "合同明细快照",
      "risk": "P0",
      "docLabels": ["委托加工金额"],
      "requiredScenarioKeys": [
        "derived_amount_recomputed",
        "manual_snapshot_retained"
      ],
      "status": "covered",
      "layers": ["web"],
      "passedCases": 4,
      "totalCases": 4,
      "passedScenarios": 2,
      "totalScenarios": 2,
      "scenarios": [
        {
          "scenarioKey": "derived_amount_recomputed",
          "scenarioLabel": "数量与单价驱动金额重算",
          "status": "pass",
          "caseIds": [
            "FL_processing_contract_amount__derives_default_line_amount_snapshot",
            "FL_processing_contract_editor__recomputes_default_amount_on_quantity_change"
          ]
        },
        {
          "scenarioKey": "manual_snapshot_retained",
          "scenarioLabel": "手工金额快照优先保留",
          "status": "pass",
          "caseIds": [
            "FL_processing_contract_amount__keeps_manual_line_amount_snapshot",
            "FL_processing_contract_editor__keeps_manual_amount_on_quantity_change"
          ]
        }
      ],
      "cases": [
        {
          "caseId": "FL_processing_contract_amount__derives_default_line_amount_snapshot",
          "title": "加工合同默认金额按数量和单价写入合同快照",
          "fieldKeys": ["processingAmount", "itemQuantity", "itemUnitPrice"],
          "scenarioKey": "derived_amount_recomputed",
          "layer": "web",
          "testFile": "web/src/erp/data/processingContractTemplate.test.mjs",
          "status": "pass",
          "durationMs": 0,
          "failureMessages": []
        },
        {
          "caseId": "FL_processing_contract_amount__keeps_manual_line_amount_snapshot",
          "title": "加工合同已有委托加工金额时优先保留手工快照",
          "fieldKeys": ["processingAmount"],
          "scenarioKey": "manual_snapshot_retained",
          "layer": "web",
          "testFile": "web/src/erp/data/processingContractTemplate.test.mjs",
          "status": "pass",
          "durationMs": 0,
          "failureMessages": []
        },
        {
          "caseId": "FL_processing_contract_editor__recomputes_default_amount_on_quantity_change",
          "title": "加工合同调整数量时同步重算默认委托加工金额",
          "fieldKeys": ["processingAmount", "itemQuantity", "itemUnitPrice"],
          "scenarioKey": "derived_amount_recomputed",
          "layer": "web",
          "testFile": "web/src/erp/utils/processingContractEditor.test.mjs",
          "status": "pass",
          "durationMs": 0,
          "failureMessages": []
        },
        {
          "caseId": "FL_processing_contract_editor__keeps_manual_amount_on_quantity_change",
          "title": "加工合同已手工改写金额时数量变化不覆盖手工值",
          "fieldKeys": ["processingAmount"],
          "scenarioKey": "manual_snapshot_retained",
          "layer": "web",
          "testFile": "web/src/erp/utils/processingContractEditor.test.mjs",
          "status": "pass",
          "durationMs": 0,
          "failureMessages": []
        }
      ]
    },
    {
      "fieldKey": "productDescription",
      "fieldLabel": "产品描述",
      "category": "主数据快照字段",
      "risk": "P1",
      "docLabels": ["中文描述", "英文描述"],
      "requiredScenarioKeys": ["product_description_mirrored"],
      "status": "missing",
      "layers": [],
      "passedCases": 0,
      "totalCases": 0,
      "passedScenarios": 0,
      "totalScenarios": 1,
      "scenarios": [
        {
          "scenarioKey": "product_description_mirrored",
          "scenarioLabel": "产品中文描述同步快照字段",
          "status": "missing",
          "caseIds": []
        }
      ],
      "cases": []
    },
    {
      "fieldKey": "orderDate",
      "fieldLabel": "下单日期",
      "category": "日期快照字段",
      "risk": "P1",
      "docLabels": ["下单日期"],
      "requiredScenarioKeys": ["source_snapshot_retained"],
      "status": "missing",
      "layers": [],
      "passedCases": 0,
      "totalCases": 0,
      "passedScenarios": 0,
      "totalScenarios": 1,
      "scenarios": [
        {
          "scenarioKey": "source_snapshot_retained",
          "scenarioLabel": "来源快照保留并随状态流转带出",
          "status": "missing",
          "caseIds": []
        }
      ],
      "cases": []
    },
    {
      "fieldKey": "mergedCellContent",
      "fieldLabel": "合并单元格覆盖内容",
      "category": "打印编辑防残值",
      "risk": "P1",
      "docLabels": ["合并单元格覆盖内容"],
      "requiredScenarioKeys": ["merge_clears_covered_cells"],
      "status": "covered",
      "layers": ["web"],
      "passedCases": 2,
      "totalCases": 2,
      "passedScenarios": 1,
      "totalScenarios": 1,
      "scenarios": [
        {
          "scenarioKey": "merge_clears_covered_cells",
          "scenarioLabel": "合并覆盖格会清空旧值",
          "status": "pass",
          "caseIds": [
            "FL_material_purchase_merge__clears_covered_cell_stale_value",
            "FL_processing_contract_editor__clears_covered_cell_stale_value"
          ]
        }
      ],
      "cases": [
        {
          "caseId": "FL_material_purchase_merge__clears_covered_cell_stale_value",
          "title": "采购合同合并选区后会清空被覆盖单元格",
          "fieldKeys": ["productOrderNo", "mergedCellContent"],
          "scenarioKey": "merge_clears_covered_cells",
          "layer": "web",
          "testFile": "web/src/erp/utils/materialPurchaseContractEditor.test.mjs",
          "status": "pass",
          "durationMs": 0,
          "failureMessages": []
        },
        {
          "caseId": "FL_processing_contract_editor__clears_covered_cell_stale_value",
          "title": "加工合同合并选区后会清空被覆盖单元格",
          "fieldKeys": ["productOrderNo", "mergedCellContent"],
          "scenarioKey": "merge_clears_covered_cells",
          "layer": "web",
          "testFile": "web/src/erp/utils/processingContractEditor.test.mjs",
          "status": "pass",
          "durationMs": 13,
          "failureMessages": []
        }
      ]
    },
    {
      "fieldKey": "attachmentSnapshot",
      "fieldLabel": "图片 / 附件",
      "category": "附件 / 资料层字段",
      "risk": "P1",
      "docLabels": ["图片 / 附件"],
      "requiredScenarioKeys": ["print_window_snapshot_retained"],
      "status": "covered",
      "layers": ["web"],
      "passedCases": 1,
      "totalCases": 1,
      "passedScenarios": 1,
      "totalScenarios": 1,
      "scenarios": [
        {
          "scenarioKey": "print_window_snapshot_retained",
          "scenarioLabel": "打印窗口快照持久化",
          "status": "pass",
          "caseIds": [
            "FL_print_workspace_window_snapshot__persists_current_html_snapshot"
          ]
        }
      ],
      "cases": [
        {
          "caseId": "FL_print_workspace_window_snapshot__persists_current_html_snapshot",
          "title": "打印工作台会把整窗 HTML 快照落到窗口状态",
          "fieldKeys": ["attachmentSnapshot", "printWindowHtml"],
          "scenarioKey": "print_window_snapshot_retained",
          "layer": "web",
          "testFile": "web/src/erp/utils/printWorkspace.test.mjs",
          "status": "pass",
          "durationMs": 0,
          "failureMessages": []
        }
      ]
    },
    {
      "fieldKey": "settlementTerms",
      "fieldLabel": "结算方式 / 条款",
      "category": "合同条款快照（本轮排除）",
      "risk": "P2",
      "docLabels": ["结算方式 / 条款"],
      "requiredScenarioKeys": ["contract_terms_excluded_from_business_scope"],
      "status": "covered",
      "layers": ["qa"],
      "passedCases": 1,
      "totalCases": 1,
      "passedScenarios": 1,
      "totalScenarios": 1,
      "scenarios": [
        {
          "scenarioKey": "contract_terms_excluded_from_business_scope",
          "scenarioLabel": "合同条款字段本轮排除在业务表单外",
          "status": "pass",
          "caseIds": [
            "FL_contract_terms__excluded_from_non_contract_business_scope"
          ]
        }
      ],
      "cases": [
        {
          "caseId": "FL_contract_terms__excluded_from_non_contract_business_scope",
          "title": "合同正文、条款和打印专用字段本轮不作为业务表单字段",
          "fieldKeys": ["settlementTerms"],
          "scenarioKey": "contract_terms_excluded_from_business_scope",
          "layer": "qa",
          "testFile": "web/src/erp/qa/fieldLinkageCatalog.test.mjs",
          "status": "pass",
          "durationMs": 0,
          "failureMessages": []
        }
      ]
    }
  ],
  "cases": [
    {
      "caseId": "FL_contract_terms__excluded_from_non_contract_business_scope",
      "title": "合同正文、条款和打印专用字段本轮不作为业务表单字段",
      "fieldKeys": ["settlementTerms"],
      "scenarioKey": "contract_terms_excluded_from_business_scope",
      "layer": "qa",
      "testFile": "web/src/erp/qa/fieldLinkageCatalog.test.mjs",
      "status": "pass",
      "durationMs": 0,
      "failureMessages": []
    },
    {
      "caseId": "FL_processing_contract_amount__derives_default_line_amount_snapshot",
      "title": "加工合同默认金额按数量和单价写入合同快照",
      "fieldKeys": ["processingAmount", "itemQuantity", "itemUnitPrice"],
      "scenarioKey": "derived_amount_recomputed",
      "layer": "web",
      "testFile": "web/src/erp/data/processingContractTemplate.test.mjs",
      "status": "pass",
      "durationMs": 0,
      "failureMessages": []
    },
    {
      "caseId": "FL_processing_contract_amount__keeps_manual_line_amount_snapshot",
      "title": "加工合同已有委托加工金额时优先保留手工快照",
      "fieldKeys": ["processingAmount"],
      "scenarioKey": "manual_snapshot_retained",
      "layer": "web",
      "testFile": "web/src/erp/data/processingContractTemplate.test.mjs",
      "status": "pass",
      "durationMs": 0,
      "failureMessages": []
    },
    {
      "caseId": "FL_material_purchase_amount__recomputes_amount_and_total_from_current_line",
      "title": "采购合同数量或单价变化会重算金额和总计",
      "fieldKeys": ["purchaseAmount", "itemQuantity", "itemUnitPrice"],
      "scenarioKey": "derived_amount_recomputed",
      "layer": "web",
      "testFile": "web/src/erp/utils/materialPurchaseContractEditor.test.mjs",
      "status": "pass",
      "durationMs": 1,
      "failureMessages": []
    },
    {
      "caseId": "FL_material_purchase_amount__keeps_manual_amount_snapshot",
      "title": "采购合同初始化时优先保留已有采购金额快照",
      "fieldKeys": ["purchaseAmount"],
      "scenarioKey": "manual_snapshot_retained",
      "layer": "web",
      "testFile": "web/src/erp/utils/materialPurchaseContractEditor.test.mjs",
      "status": "pass",
      "durationMs": 1,
      "failureMessages": []
    },
    {
      "caseId": "FL_material_purchase_merge__clears_covered_cell_stale_value",
      "title": "采购合同合并选区后会清空被覆盖单元格",
      "fieldKeys": ["productOrderNo", "mergedCellContent"],
      "scenarioKey": "merge_clears_covered_cells",
      "layer": "web",
      "testFile": "web/src/erp/utils/materialPurchaseContractEditor.test.mjs",
      "status": "pass",
      "durationMs": 0,
      "failureMessages": []
    },
    {
      "caseId": "FL_processing_contract_editor__clears_blank_inserted_lines",
      "title": "加工合同插入明细行会清空来源字段，避免复制当前行残值",
      "fieldKeys": ["productOrderNo", "productNo", "productNameColor"],
      "scenarioKey": "stale_value_cleared",
      "layer": "web",
      "testFile": "web/src/erp/utils/processingContractEditor.test.mjs",
      "status": "pass",
      "durationMs": 1,
      "failureMessages": []
    },
    {
      "caseId": "FL_processing_contract_editor__clears_deleted_last_line",
      "title": "加工合同删除到只剩一行时会重置为空白行",
      "fieldKeys": ["productOrderNo", "productNo", "productNameColor"],
      "scenarioKey": "stale_value_cleared",
      "layer": "web",
      "testFile": "web/src/erp/utils/processingContractEditor.test.mjs",
      "status": "pass",
      "durationMs": 0,
      "failureMessages": []
    },
    {
      "caseId": "FL_processing_contract_editor__clears_covered_cell_stale_value",
      "title": "加工合同合并选区后会清空被覆盖单元格",
      "fieldKeys": ["productOrderNo", "mergedCellContent"],
      "scenarioKey": "merge_clears_covered_cells",
      "layer": "web",
      "testFile": "web/src/erp/utils/processingContractEditor.test.mjs",
      "status": "pass",
      "durationMs": 13,
      "failureMessages": []
    },
    {
      "caseId": "FL_processing_contract_editor__recomputes_default_amount_on_quantity_change",
      "title": "加工合同调整数量时同步重算默认委托加工金额",
      "fieldKeys": ["processingAmount", "itemQuantity", "itemUnitPrice"],
      "scenarioKey": "derived_amount_recomputed",
      "layer": "web",
      "testFile": "web/src/erp/utils/processingContractEditor.test.mjs",
      "status": "pass",
      "durationMs": 0,
      "failureMessages": []
    },
    {
      "caseId": "FL_processing_contract_editor__keeps_manual_amount_on_quantity_change",
      "title": "加工合同已手工改写金额时数量变化不覆盖手工值",
      "fieldKeys": ["processingAmount"],
      "scenarioKey": "manual_snapshot_retained",
      "layer": "web",
      "testFile": "web/src/erp/utils/processingContractEditor.test.mjs",
      "status": "pass",
      "durationMs": 0,
      "failureMessages": []
    },
    {
      "caseId": "FL_print_workspace_window_snapshot__persists_current_html_snapshot",
      "title": "打印工作台会把整窗 HTML 快照落到窗口状态",
      "fieldKeys": ["attachmentSnapshot", "printWindowHtml"],
      "scenarioKey": "print_window_snapshot_retained",
      "layer": "web",
      "testFile": "web/src/erp/utils/printWorkspace.test.mjs",
      "status": "pass",
      "durationMs": 0,
      "failureMessages": []
    },
    {
      "caseId": "FL_print_templates_sample__uses_generic_sample_values_without_customer_identity",
      "title": "打印模板默认样例使用中性展示值且不带客户身份",
      "fieldKeys": ["processorContactAddress"],
      "scenarioKey": "default_sample_uses_generic_party_values",
      "layer": "web",
      "testFile": "web/src/erp/config/printTemplates.test.mjs",
      "status": "pass",
      "durationMs": 1,
      "failureMessages": []
    }
  ]
}
